typewriter/__main__.py
typewriter/typewriter.py
typewriter/backup/typewriter.py
typerwriter-0.0.2.dist-info/LICENSE
typerwriter-0.0.2.dist-info/METADATA
typerwriter-0.0.2.dist-info/WHEEL
typerwriter-0.0.2.dist-info/entry_points.txt
typerwriter-0.0.2.dist-info/top_level.txt
typerwriter-0.0.2.dist-info/RECORD
