Metadata-Version: 2.1
Name: typerwriter
Version: 0.0.2
Summary: A fast runtime type annotator for Python code.
Author-email: Emery Berger <emery.berger@gmail.com>
Project-URL: Homepage, https://github.com/plasma-umass/typerwriter
Project-URL: Bug Tracker, https://github.com/plasma-umass/typerwriter
Classifier: Programming Language :: Python :: 3
Classifier: License :: OSI Approved :: MIT License
Classifier: Operating System :: OS Independent
Requires-Python: >=3.12
License-File: LICENSE
